calculadora_do_cidadao/__init__.py
calculadora_do_cidadao/__main__.py
calculadora_do_cidadao/adapters/__init__.py
calculadora_do_cidadao/adapters/cpi.py
calculadora_do_cidadao/adapters/dieese.py
calculadora_do_cidadao/adapters/ibge.py
calculadora_do_cidadao/adapters/igpm.py
calculadora_do_cidadao/adapters/selic.py
calculadora_do_cidadao/download.py
calculadora_do_cidadao/fields.py
calculadora_do_cidadao/months.py
calculadora_do_cidadao/rows/__init__.py
calculadora_do_cidadao/rows/fields.py
calculadora_do_cidadao/rows/plugins/__init__.py
calculadora_do_cidadao/rows/plugins/dicts.py
calculadora_do_cidadao/rows/plugins/plugin_csv.py
calculadora_do_cidadao/rows/plugins/plugin_html.py
calculadora_do_cidadao/rows/plugins/utils.py
calculadora_do_cidadao/rows/plugins/xls.py
calculadora_do_cidadao/rows/table.py
calculadora_do_cidadao/typing.py
calculadora_do_cidadao-1.0.0.dist-info/LICENSE
calculadora_do_cidadao-1.0.0.dist-info/WHEEL
calculadora_do_cidadao-1.0.0.dist-info/METADATA
calculadora_do_cidadao-1.0.0.dist-info/RECORD
