Metadata-Version: 2.1
Name: calculadora-do-cidadao
Version: 1.0.0
Summary: Tool for Brazilian Reais monetary adjustment/correction
Home-page: https://calculadora-do-cidadao.readthedocs.io/
License: GPLv3
Keywords: Brazil,Brazilian Reais,monetary adjusment,monetary correction,Inflation
Author: Eduardo Cuducos
Author-email: cuducos@users.noreply.github.com
Requires-Python: >=3.7,<4.0
Classifier: Development Status :: 4 - Beta
Classifier: Intended Audience :: Developers
Classifier: Intended Audience :: End Users/Desktop
Classifier: License :: OSI Approved :: GNU General Public License v3 (GPLv3)
Classifier: License :: Other/Proprietary License
Classifier: Programming Language :: Python :: 3
Classifier: Programming Language :: Python :: 3.10
Classifier: Programming Language :: Python :: 3.7
Classifier: Programming Language :: Python :: 3.8
Classifier: Programming Language :: Python :: 3.9
Classifier: Topic :: Utilities
Provides-Extra: docs
Requires-Dist: lxml (>=4.7.1,<5.0.0)
Requires-Dist: pip (>=20.0.0); extra == "docs"
Requires-Dist: readthedocs-sphinx-ext (>=2.1.3); extra == "docs"
Requires-Dist: requests (>=2.22.0)
Requires-Dist: sphinx (>=3.4.3); extra == "docs"
Requires-Dist: sphinx-rtd-theme (>=0.5.1); extra == "docs"
Requires-Dist: typer (>=0.0.8)
Requires-Dist: unicodecsv (>=0.14.1,<0.15.0)
Requires-Dist: xlrd (>=2.0.1,<3.0.0)
Requires-Dist: xlwt (>=1.3.0,<2.0.0)
Project-URL: Repository, https://github.com/cuducos/calculadora-do-cidadao/
